sisif/__init__.py
sisif-0.0.1.dist-info/METADATA
sisif-0.0.1.dist-info/WHEEL
sisif-0.0.1.dist-info/top_level.txt
sisif-0.0.1.dist-info/RECORD
