Metadata-Version: 2.4
Name: sisif
Version: 0.0.1
Summary: Spatial Intelligence Scene Interaction Format
Author-email: Yunus Skeete <yunus@spatial-intelligence.co.uk>
Classifier: Development Status :: 1 - Planning
Classifier: Programming Language :: Python :: 3
Requires-Python: >=3.9
